Metadata-Version: 2.4
Name: pandas-plink-ng
Version: 2.3.3
Summary: Fork of pandas-plink with NumPy >=2.0 support and modern Python/GPU-stack compatibility
License: MIT
License-File: LICENSE.md
Keywords: plink,reader,genetics,genomics,QTL,fork
Author: Danilo Horta
Author-email: danilo.horta@pm.me
Requires-Python: >=3.11,<3.15
Classifier: Intended Audience :: Science/Research
Classifier: License :: OSI Approved :: MIT License
Classifier: Programming Language :: Python :: 3
Classifier: Programming Language :: Python :: 3.11
Classifier: Programming Language :: Python :: 3.12
Classifier: Programming Language :: Python :: 3.13
Classifier: Programming Language :: Python :: 3.14
Classifier: Programming Language :: Python :: 3 :: Only
Classifier: Topic :: Scientific/Engineering :: Bio-Informatics
Classifier: Topic :: Scientific/Engineering :: Information Analysis
Requires-Dist: cffi (>=1.17)
Requires-Dist: dask[dataframe]
Requires-Dist: deprecated (>=1.2,<2.0)
Requires-Dist: numpy (>=2,<3)
Requires-Dist: pandas (>=2.2,<3.0)
Requires-Dist: pandera[dask,mypy]
Requires-Dist: tqdm (>=4.67,<5.0)
Requires-Dist: xarray
Requires-Dist: zstandard (>=0.23,<0.26)
Project-URL: Homepage, https://github.com/KrotosBenjamin/pandas-plink-ng
Project-URL: Repository, https://github.com/KrotosBenjamin/pandas-plink-ng
